{"type":"FeatureCollection","features":[{"type":"Feature","id":0,"geometry":{"type":"Point","coordinates":[80.617795398921032,28.770921396296504]},"properties":{"FID":0,"VDC_NAME":"Beladevipur","DIST_NAME":"Kailali"}},{"type":"Feature","id":1,"geometry":{"type":"Point","coordinates":[80.719946649050314,28.754199786846868]},"properties":{"FID":1,"VDC_NAME":"Chaumala","DIST_NAME":"Kailali"}},{"type":"Feature","id":2,"geometry":{"type":"Point","coordinates":[80.599131214101135,28.69033966271201]},"properties":{"FID":2,"VDC_NAME":"Dhangadhi N.P.","DIST_NAME":"Kailali"}},{"type":"Feature","id":3,"geometry":{"type":"Point","coordinates":[80.682256887825815,28.693263277804249]},"properties":{"FID":3,"VDC_NAME":"Urma","DIST_NAME":"Kailali"}}]}